broken_flask_client/__init__.py
broken_flask_client/employees.py
broken_flask_client/version.py
broken_flask_client-0.2.0.dist-info/METADATA
broken_flask_client-0.2.0.dist-info/WHEEL
broken_flask_client-0.2.0.dist-info/top_level.txt
broken_flask_client-0.2.0.dist-info/zip-safe
broken_flask_client-0.2.0.dist-info/RECORD
