Metadata-Version: 2.1
Name: broken-flask-client
Version: 0.2.0
Summary: Client for the broken-flask app
Home-page: https://github.com/nvsecurity/broken-flask
Author: Kinnaird McQuade
Author-email: kinnairdm@gmail.com
Keywords: aws iam security
Classifier: Programming Language :: Python :: 3
Classifier: License :: OSI Approved :: MIT License
Classifier: Operating System :: OS Independent
Requires-Python: >=3.7
Requires-Dist: requests
